<Room>
  <Saves />
  <index>00</index>
  <area>02</area>
  <x>04</x>
  <y>03</y>
  <width>02</width>
  <height>01</height>
  <upscroll>70</upscroll>
  <dnscroll>A0</dnscroll>
  <specialGFX>00</specialGFX>
  <Doors>
    <Door>
      <toroom area="02" index="04" />
      <bitflag>00</bitflag>
      <direction>04</direction>
      <tilex>1</tilex>
      <tiley>6</tiley>
      <screenx>03</screenx>
      <screeny>02</screeny>
      <distance>8000</distance>
      <doorcode>0000</doorcode>
    </Door>
    <Door>
      <toroom area="02" index="07" />
      <bitflag>00</bitflag>
      <direction>05</direction>
      <tilex>E</tilex>
      <tiley>6</tiley>
      <screenx>00</screenx>
      <screeny>02</screeny>
      <distance>8000</distance>
      <doorcode>0000</doorcode>
    </Door>
  </Doors>
  <States>
    <State condition="default">
      <LevelData Width="2" Height="1">
        <Layer1>
          <Screen X="0" Y="0">
        811D 811D 811D 811D 811D 811D 811D 811D 811D 811D 811D 811D 811D 811D 811D 811D
        811D 811D 811D 811D 811D 811D 811D 811D 811D 811D 811D 811D 811D 811D 811D 811D
        811D 811D 811D 8D88 8980 89A0 8980 8983 892D 892D 8921 811D 8D21 892D 892D 8D83
        811D 811D 811D 8586 00FF 00FF 00FF 00FF 00FF 00FF 8122 811D 8522 00FF 00FF 00FF
        811D 811D 8D88 8D8C 00FF 00FF 00FF 00FF 00FF 00FF 8923 8934 8D23 00FF 00FF 00FF
        8980 89A0 8D8C 00FF 00FF 00FF 00FF 00FF 00FF 00FF 00FF 8142 00FF 00FF 00FF 00FF
        9440 C40C 00FF 00FF 00FF 00FF 00FF 00FF 00FF 00FF 00FF 00FF 00FF 00FF 00FF 00FF
        9460 D42C 00FF 00FF 00FF 00FF 00FF 00FF 00FF 00FF 00FF 00FF 00FF 00FF 00FF 00FF
        9C60 DC2C 00FF 00FF 00FF 00FF 00FF 00FF 00FF 00FF 00FF 00FF 00FF 00FF 00FF 00FF
        9C40 DC0C 00FF 00FF 00FF 00FF 00FF 00FF 00FF 00FF 00FF 00FF 00FF 00FF 00FF 00FF
        849D 805F 809E 805F 00FF 00FF 00FF 00FF 00FF 00FF 805F 809E 805F 00FF 00FF 00FF
        80BB 80BD 80FF 80BD 00FF 00FF 00FF 00FF 00FF 00FF 80BD 80FF 80BD 00FF 00FF 00FF
        80BB 88BD 80FF 88BD 00FF 00FF 00FF 00FF 00FF 00FF 88BD 80FF 88BD 00FF 00FF 00FF
        8180 81A0 8180 8183 8183 81A0 8180 81A0 8183 8183 8180 81A0 8180 81A0 8183 8183
        811D 811D 811D 811D 811D 811D 811D 811D 811D 811D 811D 811D 811D 811D 811D 811D
        811D 811D 811D 811D 811D 811D 811D 811D 811D 811D 811D 811D 811D 811D 811D 811D
      </Screen>
          <Screen X="1" Y="0">
        811D 811D 811D 811D 811D 811D 811D 811D 811D 811D 811D 811D 811D 811D 811D 811D
        811D 811D 811D 811D 811D 811D 811D 811D 811D 811D 811D 811D 811D 811D 811D 811D
        8980 8983 892D 8921 811D 8D21 892D 892D 8D83 8980 89A0 8980 8988 811D 811D 811D
        00FF 00FF 00FF 8122 811D 8522 00FF 00FF 00FF 00FF 00FF 00FF 8186 811D 811D 811D
        00FF 00FF 00FF 8923 8934 8D23 00FF 00FF 00FF 00FF 00FF 00FF 898C 8988 811D 811D
        00FF 00FF 00FF 00FF 8142 00FF 00FF 00FF 00FF 00FF 00FF 00FF 00FF 898C 8980 89A0
        00FF 00FF 00FF 00FF 00FF 00FF 00FF 00FF 00FF 00FF 00FF 00FF 00FF 00FF C00C 9040
        00FF 00FF 00FF 00FF 00FF 00FF 00FF 00FF 00FF 00FF 00FF 00FF 00FF 00FF D02C 9060
        00FF 00FF 00FF 00FF 00FF 00FF 00FF 00FF 00FF 00FF 00FF 00FF 00FF 00FF D82C 9860
        00FF 00FF 00FF 00FF 00FF 00FF 00FF 00FF 00FF 00FF 00FF 00FF 00FF 00FF D80C 9840
        00FF 00FF 00FF 805F 809E 805F 00FF 00FF 00FF 00FF 00FF 00FF 805F 809E 805F 809D
        00FF 00FF 00FF 80BD 80FF 80BD 00FF 00FF 00FF 00FF 00FF 00FF 80BD 80FF 80BD 80BB
        00FF 00FF 00FF 88BD 80FF 88BD 00FF 00FF 00FF 00FF 00FF 00FF 88BD 80FF 88BD 80BB
        8180 81A0 8180 81A0 8183 8183 8180 81A0 8180 8183 8183 81A0 8180 8183 8183 81A0
        811D 811D 811D 811D 811D 811D 811D 811D 811D 811D 811D 811D 811D 811D 811D 811D
        811D 811D 811D 811D 811D 811D 811D 811D 811D 811D 811D 811D 811D 811D 811D 811D
      </Screen>
        </Layer1>
        <BTS>
          <Screen X="0" Y="0">
        00 00 00 00 00 00 00 00 00 00 00 00 00 00 00 00
        00 00 00 00 00 00 00 00 00 00 00 00 00 00 00 00
        00 00 00 00 00 00 00 00 00 00 00 00 00 00 00 00
        00 00 00 00 00 00 00 00 00 00 00 00 00 00 00 00
        00 00 00 00 00 00 00 00 00 00 00 00 00 00 00 00
        00 00 00 00 00 00 00 00 00 00 00 00 00 00 00 00
        01 41 00 00 00 00 00 00 00 00 00 00 00 00 00 00
        01 FF 00 00 00 00 00 00 00 00 00 00 00 00 00 00
        01 FE 00 00 00 00 00 00 00 00 00 00 00 00 00 00
        01 FD 00 00 00 00 00 00 00 00 00 00 00 00 00 00
        00 00 00 00 00 00 00 00 00 00 00 00 00 00 00 00
        00 00 00 00 00 00 00 00 00 00 00 00 00 00 00 00
        00 00 00 00 00 00 00 00 00 00 00 00 00 00 00 00
        00 00 00 00 00 00 00 00 00 00 00 00 00 00 00 00
        00 00 00 00 00 00 00 00 00 00 00 00 00 00 00 00
        00 00 00 00 00 00 00 00 00 00 00 00 00 00 00 00
      </Screen>
          <Screen X="1" Y="0">
        00 00 00 00 00 00 00 00 00 00 00 00 00 00 00 00
        00 00 00 00 00 00 00 00 00 00 00 00 00 00 00 00
        00 00 00 00 00 00 00 00 00 00 00 00 00 00 00 00
        00 00 00 00 00 00 00 00 00 00 00 00 00 00 00 00
        00 00 00 00 00 00 00 00 00 00 00 00 00 00 00 00
        00 00 00 00 00 00 00 00 00 00 00 00 00 00 00 00
        00 00 00 00 00 00 00 00 00 00 00 00 00 00 40 00
        00 00 00 00 00 00 00 00 00 00 00 00 00 00 FF 00
        00 00 00 00 00 00 00 00 00 00 00 00 00 00 FE 00
        00 00 00 00 00 00 00 00 00 00 00 00 00 00 FD 00
        00 00 00 00 00 00 00 00 00 00 00 00 00 00 00 00
        00 00 00 00 00 00 00 00 00 00 00 00 00 00 00 00
        00 00 00 00 00 00 00 00 00 00 00 00 00 00 00 00
        00 00 00 00 00 00 00 00 00 00 00 00 00 00 00 00
        00 00 00 00 00 00 00 00 00 00 00 00 00 00 00 00
        00 00 00 00 00 00 00 00 00 00 00 00 00 00 00 00
      </Screen>
        </BTS>
        <Layer2>
          <Screen X="0" Y="0">
        00FF 00FF 0273 0274 00FF 00FF 00FF 00FF 00FF 00FF 00FF 00FF 00FF 00FF 00FF 00FF
        00FF 00FF 0293 0294 00FF 00FF 00FF 00FF 00FF 00FF 00FF 0257 00FF 00FF 00FF 0273
        00FF 00FF 027E 027F 00FF 0273 0274 00FF 00FF 00FF 00FF 0297 00FF 00FF 00FF 0293
        00FF 00FF 0295 0296 00FF 0293 0294 00FF 0257 00FF 00FF 00FF 00FF 025C 025D 027E
        0273 0274 025E 025F 00FF 027E 027F 00FF 0277 00FF 00FF 00FF 00FF 027C 027D 0295
        0293 0294 027E 027F 00FF 0295 0296 00FF 0277 00FF 00FF 00FF 00FF 0295 0296 025E
        027E 027F 0295 0296 00FF 025E 025F 00FF 0277 00FF 00FF 0273 0274 0258 0259 027E
        0295 0296 025E 025F 00FF 027E 027F 00FF 0277 0257 00FF 0293 0294 0278 0279 0295
        025E 025F 027E 027F 00FF 0295 0296 00FF 0277 0277 00FF 027E 027F 00FF 00FF 025E
        027E 027F 0295 0296 00FF 025E 025F 00FF 0297 0277 00FF 0295 0296 00FF 00FF 027E
        0295 0296 025E 025F 00FF 027E 027F 00FF 00FF 0277 00FF 025E 025F 0257 00FF 0295
        025E 025F 027E 027F 00FF 0295 0296 00FF 00FF 0277 00FF 027E 027F 0277 00FF 025E
        027E 027F 0295 0296 00FF 025E 025F 00FF 00FF 0277 00FF 0295 0296 0277 00FF 027E
        0295 0296 0258 0259 00FF 027E 027F 00FF 00FF 0297 00FF 025E 025F 0277 00FF 0295
        025E 025F 0278 0279 00FF 0295 0296 0257 00FF 00FF 00FF 027E 027F 0277 00FF 0258
        027E 027F 00FF 00FF 00FF 0258 0259 0277 00FF 00FF 00FF 0295 0296 0277 00FF 0278
      </Screen>
          <Screen X="1" Y="0">
        00FF 00FF 00FF 00FF 00FF 00FF 00FF 00FF 00FF 00FF 00FF 00FF 00FF 00FF 00FF 00FF
        0274 00FF 0257 00FF 00FF 00FF 00FF 00FF 00FF 00FF 0273 0274 0257 00FF 00FF 00FF
        0294 00FF 0277 00FF 00FF 00FF 00FF 00FF 00FF 00FF 0293 0294 0277 00FF 00FF 00FF
        027F 00FF 0277 00FF 00FF 00FF 00FF 00FF 00FF 00FF 027E 027F 0277 00FF 0273 0274
        0296 00FF 0277 00FF 00FF 00FF 00FF 00FF 00FF 00FF 0295 0296 0277 00FF 0293 0294
        025F 00FF 0277 00FF 00FF 00FF 00FF 00FF 00FF 00FF 025E 025F 0277 00FF 027E 027F
        027F 00FF 0277 00FF 00FF 00FF 00FF 025C 025D 00FF 027E 027F 0277 00FF 0295 0296
        0296 00FF 0297 00FF 00FF 00FF 00FF 027C 027D 00FF 0295 0296 0297 00FF 025E 025F
        025F 00FF 00FF 00FF 0257 00FF 00FF 0295 0296 00FF 025E 025F 00FF 00FF 027E 027F
        027F 00FF 00FF 00FF 0277 00FF 00FF 0258 0259 00FF 027E 027F 00FF 00FF 0295 0296
        0296 00FF 00FF 00FF 0277 00FF 00FF 0278 0279 00FF 0295 0296 00FF 00FF 025E 025F
        025F 00FF 00FF 00FF 0277 00FF 00FF 00FF 00FF 00FF 025E 025F 00FF 00FF 027E 027F
        027F 0257 00FF 00FF 0277 00FF 00FF 00FF 00FF 00FF 027E 027F 00FF 00FF 0295 0296
        0296 0277 00FF 00FF 0277 00FF 0257 00FF 00FF 00FF 0295 0296 00FF 00FF 025E 025F
        0259 0277 00FF 00FF 0297 00FF 0277 00FF 00FF 00FF 0258 0259 00FF 00FF 027E 027F
        0279 0277 00FF 00FF 00FF 00FF 0277 00FF 00FF 00FF 0278 0279 00FF 00FF 0295 0296
      </Screen>
        </Layer2>
      </LevelData>
      <GFXset>0B</GFXset>
      <music>0000</music>
      <FX1s>
        <FX1 default="true">
          <surfacestart>00B8</surfacestart>
          <surfacenew>FFFF</surfacenew>
          <surfacespeed>0000</surfacespeed>
          <surfacedelay>00</surfacedelay>
          <type>02</type>
          <transparency1_A>02</transparency1_A>
          <transparency2_B>1E</transparency2_B>
          <liquidflags_C>0B</liquidflags_C>
          <paletteflags>80</paletteflags>
          <animationflags>02</animationflags>
          <paletteblend>02</paletteblend>
        </FX1>
      </FX1s>
      <Enemies killcount="03">
        <Enemy>
          <ID>D7FF</ID>
          <X>0190</X>
          <Y>00A8</Y>
          <tilemap>0000</tilemap>
          <special>A000</special>
          <gfx>0000</gfx>
          <speed>0000</speed>
          <speed2>1010</speed2>
        </Enemy>
        <Enemy>
          <ID>D7FF</ID>
          <X>0100</X>
          <Y>00A8</Y>
          <tilemap>0000</tilemap>
          <special>A000</special>
          <gfx>0000</gfx>
          <speed>0000</speed>
          <speed2>1010</speed2>
        </Enemy>
        <Enemy>
          <ID>D7FF</ID>
          <X>0070</X>
          <Y>00A8</Y>
          <tilemap>0000</tilemap>
          <special>A000</special>
          <gfx>0000</gfx>
          <speed>0000</speed>
          <speed2>1010</speed2>
        </Enemy>
      </Enemies>
      <EnemyTypes>
        <Enemy>
          <GFX>D7FF</GFX>
          <palette>0007</palette>
        </Enemy>
      </EnemyTypes>
      <layer2_type>Layer2</layer2_type>
      <layer2_xscroll>C0</layer2_xscroll>
      <layer2_yscroll>C0</layer2_yscroll>
      <ScrollData const="0000" />
      <roomvar>0000</roomvar>
      <FX2>0000</FX2>
      <PLMs />
      <BGData />
      <layer1_2>91F5</layer1_2>
    </State>
  </States>
</Room>