<Room>
  <Saves />
  <index>03</index>
  <area>00</area>
  <x>20</x>
  <y>01</y>
  <width>02</width>
  <height>01</height>
  <upscroll>70</upscroll>
  <dnscroll>A0</dnscroll>
  <specialGFX>00</specialGFX>
  <Doors>
    <Door>
      <toroom area="00" index="00" />
      <bitflag>00</bitflag>
      <direction>05</direction>
      <tilex>E</tilex>
      <tiley>6</tiley>
      <screenx>08</screenx>
      <screeny>01</screeny>
      <distance>8000</distance>
      <doorcode>0000</doorcode>
    </Door>
  </Doors>
  <States>
    <State condition="default">
      <LevelData Width="2" Height="1">
        <Layer1>
          <Screen X="0" Y="0">
        8101 8101 8101 8101 8101 8101 8101 8101 8101 8101 8101 8101 8101 8101 8101 8101
        8101 8101 8101 8101 8101 8101 8101 8101 8101 8104 8101 8101 8101 8101 8101 8101
        8111 8111 8111 8107 8100 8507 8111 8115 8117 81B3 8111 8107 8100 8507 8111 8134
        8101 8101 1620 00FF 81A6 018E 1236 1111 8111 1111 1237 018D 81A6 1236 1111 8111
        8101 8120 00FF 00FF 81A6 01AE 01AF 1236 1237 00FF 01AC 01AD 81A6 01AF 00FF 1236
        8101 8120 00FF 00FF 00FF 00FF 00FF 0256 0257 00FF 00FF 00FF A856 00FF 00FF 0256
        9440 C40C 00FF 00FF 00FF 00FF 00FF 00FF 00FF 00FF 00FF 00FF 00FF 00FF 00FF 00FF
        9460 D42C 00FF 00FF 00FF 00FF 00FF 00FF 00FF 00FF 00FF 00FF 00FF 00FF 00FF 00FF
        9C60 DC2C 00FF 00FF 00FF 00FF 00FF 00FF 00FF 00FF 00FF 00FF 00FF 00FF 00FF 00FF
        9C40 DC0C 00FF 00FF 00FF 00FF 00FF 00FF 00FF 00FF 00FF 00FF 00FF 00FF 00FF 00FF
        812D 812D 8163 812D 8527 00FF 00FF 00FF 81A9 00FF 00FF 00FF 00FF 00FF 00FF 00FF
        8111 8111 8111 81C6 81C7 00FF 00FF 00FF 81A8 00FF 00FF 00FF 81A9 00FF 00FF 00FF
        8111 8111 8111 8186 8187 00FF 1108 110A 112D 8162 8163 812D 850A 1508 00FF 1108
        8111 8111 8111 8144 852E 812D 8128 814A 8124 8129 8124 814A 8124 8528 812D 8128
        8111 8111 8111 8111 8111 8111 8111 8111 8111 8111 8111 8111 8111 8111 8111 8111
        8111 8111 8111 8111 8111 8111 8111 8111 8111 8111 8111 8111 8111 8111 8111 8111
      </Screen>
          <Screen X="1" Y="0">
        8101 8101 8101 8101 8101 8101 8101 8101 8101 8101 8101 8101 8101 8101 8101 8101
        8101 8101 8101 8101 8101 8104 8101 8101 8104 8101 8101 8101 8101 8101 8101 8101
        8135 8111 8107 8100 8507 8111 8115 8117 8111 8107 8100 8507 8111 8176 8134 8135
        1111 1237 018D 81A6 1236 1111 8111 8111 1111 1237 81A6 00FF 1220 1103 8101 8101
        1237 01AC 01AD 81A6 0256 018E 1236 1111 1237 018D 81A6 00FF 00FF 00FF 1220 8101
        0257 00FF 00FF A856 00FF 01AE 0256 00FF 0257 01AD 00FF 00FF 00FF 00FF 00FF 8520
        00FF 00FF 00FF 00FF 00FF 00FF 00FF 00FF 00FF 00FF 00FF 00FF 00FF 00FF 00FF 8520
        00FF 00FF 00FF 00FF 00FF 00FF 00FF 00FF 00FF 00FF 00FF 00FF 00FF 00FF 00FF 8520
        00FF 00FF 00FF 00FF 00FF 00FF 00FF 00FF 00FF 00FF 00FF 00FF 00FF 805D 00FF 8520
        00FF 00FF 00FF 00FF 00FF 00FF 00FF 00FF 00FF 00FF 00FF 8127 812D 8162 812D 812E
        81A9 00FF 00FF 00FF 00FF 00FF 00FF 81A9 00FF 00FF 00FF 8186 8187 8111 8111 8111
        81A8 00FF 00FF 81A9 00FF 00FF 00FF 81A8 00FF 00FF 00FF 8186 8187 8111 8176 8135
        810A 812D 8163 850A 1508 00FF 1108 810A 8163 8162 8167 8124 8544 8111 81B3 8134
        8124 814A 8124 8129 8528 812D 8128 8129 8124 8129 8123 8129 8544 8111 8111 8111
        8111 8111 8111 8111 8111 8111 8111 8111 8111 8111 8111 8111 8111 8111 8111 8111
        8111 8111 8111 8111 8111 8111 8111 8111 8111 8111 8111 8111 8111 8111 8111 8111
      </Screen>
        </Layer1>
        <BTS>
          <Screen X="0" Y="0">
        00 00 00 00 00 00 00 00 00 00 00 00 00 00 00 00
        00 00 00 00 00 00 00 00 00 00 00 00 00 00 00 00
        00 00 00 00 00 00 00 00 00 00 00 00 00 00 00 00
        00 00 D2 00 00 00 92 D3 00 D3 D2 00 00 92 D3 00
        00 00 00 00 00 00 00 92 D2 00 00 00 00 00 00 92
        00 00 00 00 00 00 00 00 00 00 00 00 00 00 00 00
        00 41 00 00 00 00 00 00 00 00 00 00 00 00 00 00
        00 FF 00 00 00 00 00 00 00 00 00 00 00 00 00 00
        00 FE 00 00 00 00 00 00 00 00 00 00 00 00 00 00
        00 FD 00 00 00 00 00 00 00 00 00 00 00 00 00 00
        00 00 00 00 00 00 00 00 00 00 00 00 00 00 00 00
        00 00 00 00 00 00 00 00 00 00 00 00 00 00 00 00
        00 00 00 00 00 00 12 13 13 00 00 00 00 52 00 12
        00 00 00 00 00 00 00 00 00 00 00 00 00 00 00 00
        00 00 00 00 00 00 00 00 00 00 00 00 00 00 00 00
        00 00 00 00 00 00 00 00 00 00 00 00 00 00 00 00
      </Screen>
          <Screen X="1" Y="0">
        00 00 00 00 00 00 00 00 00 00 00 00 00 00 00 00
        00 00 00 00 00 00 00 00 00 00 00 00 00 00 00 00
        00 00 00 00 00 00 00 00 00 00 00 00 00 00 00 00
        D3 D2 00 00 92 D3 00 00 D3 D2 00 00 92 D3 00 00
        D2 00 00 00 00 00 92 D3 D2 00 00 00 00 00 92 00
        00 00 00 00 00 00 00 00 00 00 00 00 00 00 00 00
        00 00 00 00 00 00 00 00 00 00 00 00 00 00 00 00
        00 00 00 00 00 00 00 00 00 00 00 00 00 00 00 00
        00 00 00 00 00 00 00 00 00 00 00 00 00 00 00 00
        00 00 00 00 00 00 00 00 00 00 00 00 00 00 00 00
        00 00 00 00 00 00 00 00 00 00 00 00 00 00 00 00
        00 00 00 00 00 00 00 00 00 00 00 00 00 00 00 00
        00 00 00 00 52 00 12 00 00 00 00 00 00 00 00 00
        00 00 00 00 00 00 00 00 00 00 00 00 00 00 00 00
        00 00 00 00 00 00 00 00 00 00 00 00 00 00 00 00
        00 00 00 00 00 00 00 00 00 00 00 00 00 00 00 00
      </Screen>
        </BTS>
      </LevelData>
      <GFXset>04</GFXset>
      <music>0000</music>
      <FX1s>
        <FX1 default="true">
          <surfacestart>00C0</surfacestart>
          <surfacenew>FFFF</surfacenew>
          <surfacespeed>0000</surfacespeed>
          <surfacedelay>00</surfacedelay>
          <type>04</type>
          <transparency1_A>02</transparency1_A>
          <transparency2_B>1E</transparency2_B>
          <liquidflags_C>42</liquidflags_C>
          <paletteflags>00</paletteflags>
          <animationflags>02</animationflags>
          <paletteblend>48</paletteblend>
        </FX1>
      </FX1s>
      <Enemies killcount="03">
        <Enemy>
          <ID>E9BF</ID>
          <X>0088</X>
          <Y>00D8</Y>
          <tilemap>0000</tilemap>
          <special>2800</special>
          <gfx>0000</gfx>
          <speed>0000</speed>
          <speed2>0000</speed2>
        </Enemy>
        <Enemy>
          <ID>E9BF</ID>
          <X>0108</X>
          <Y>00D8</Y>
          <tilemap>0000</tilemap>
          <special>2800</special>
          <gfx>0000</gfx>
          <speed>0000</speed>
          <speed2>0000</speed2>
        </Enemy>
        <Enemy>
          <ID>E9BF</ID>
          <X>0178</X>
          <Y>00D8</Y>
          <tilemap>0000</tilemap>
          <special>2800</special>
          <gfx>0000</gfx>
          <speed>0000</speed>
          <speed2>0000</speed2>
        </Enemy>
      </Enemies>
      <EnemyTypes>
        <Enemy>
          <GFX>E9BF</GFX>
          <palette>0001</palette>
        </Enemy>
        <Enemy>
          <GFX>D7BF</GFX>
          <palette>0001</palette>
        </Enemy>
      </EnemyTypes>
      <layer2_type>BGData</layer2_type>
      <layer2_xscroll>C0</layer2_xscroll>
      <layer2_yscroll>C0</layer2_yscroll>
      <ScrollData const="0000" />
      <roomvar>0000</roomvar>
      <FX2>C116</FX2>
      <PLMs>
        <PLM>
          <type>EEE3</type>
          <x>1D</x>
          <y>07</y>
          <arg>0000</arg>
        </PLM>
      </PLMs>
      <BGData>
        <Data Type="DECOMP">
          <SOURCE>
            161D 0323 0323 0323 0323 0323 1598 1599 1599 1599 1599 1599 1599 1599 5599 5598 
            161D 0323 0323 0323 0323 0323 4323 561D 161D 0323 0323 0323 0323 0323 4323 561D 
            161D 0323 0323 0323 0323 0323 1598 1599 1599 1599 1599 1599 1599 1599 5599 5598 
            161D 0323 0323 0323 0323 0323 4323 561D 161D 0323 0323 0323 0323 0323 4323 561D 
            161D 0323 0323 0323 0323 0323 1598 1599 1599 1599 1599 1599 1599 1599 5599 5598 
            161D 0323 0323 0323 0323 0323 4323 561D 161D 0323 0323 0323 0323 0323 4323 561D 
            161D 0323 0323 0323 0323 0323 1598 1599 1599 1599 1599 1599 1599 1599 5599 5598 
            161D 0323 0323 0323 0323 0323 4323 561D 161D 0323 0323 0323 0323 0323 4323 561D 
            161D 0323 0323 0323 0323 0323 1598 1599 1599 1599 1599 1599 1599 1599 5599 5598 
            161D 0323 0323 0323 0323 0323 4323 561D 161D 0323 0323 0323 0323 0323 4323 561D 
            161D 0323 0323 0323 0323 0323 1598 1599 1599 1599 1599 1599 1599 1599 5599 5598 
            161D 0323 0323 0323 0323 0323 4323 561D 161D 0323 0323 0323 0323 0323 4323 561D 
            161D 0323 0323 0323 0323 0323 1598 1599 1599 1599 1599 1599 1599 1599 5599 5598 
            161D 0323 0323 0323 0323 0323 4323 561D 161D 0323 0323 0323 0323 0323 4323 561D 
            161D 0323 0323 0323 0323 0323 1598 1599 1599 1599 1599 1599 1599 1599 5599 5598 
            161D 0323 0323 0323 0323 0323 4323 561D 161D 0323 0323 0323 0323 0323 4323 561D 
            161D 0323 0323 0323 0323 0323 1598 1599 1599 1599 1599 1599 1599 1599 5599 5598 
            161D 0323 0323 0323 0323 0323 4323 561D 161D 0323 0323 0323 0323 0323 4323 561D 
            161D 0323 0323 0323 0323 0323 1598 1599 1599 1599 1599 1599 1599 1599 5599 5598 
            161D 0323 0323 0323 0323 0323 4323 561D 161D 0323 0323 0323 0323 0323 4323 561D 
            961D 8323 160F 160F 160F 160F 1598 1599 159A 159A 159A 159A 159A 159A 5599 5598 
            961D 8323 160F 160F 160F 160F C323 D61D 961D 961E 961F 961F 961F 961F D61E D61D 
            960D 960E 960E 960E 960E 960E 1598 1599 1599 1599 1599 1599 1599 1599 5599 5598 
            960D 960E 960E 960E 960E 960E D60E D60D 960D 960E 960E 960E 960E 960E D60E D60D 
            0323 0323 15EE 15EF 0323 0323 1598 1599 1599 1599 1599 1599 1599 1599 5599 5598 
            0323 0323 0323 0323 0323 0323 0323 0323 15EE 15EF 0323 0323 0323 0323 0323 0323 
            0323 0323 15EE 15EF 0323 0323 1598 1599 1599 15A7 15A8 15A9 15AA 1599 5599 5598 
            15CB 15CC 15CD 0323 0323 0323 0323 0323 15EE 15EF 0323 0323 0323 0323 0323 0323 
            0323 0323 15EE 15EF 0323 0323 1598 1599 1599 15A6 159C 159D 15AB 1599 5599 5598 
            15DB 15DC 15DD 0323 0323 0323 0323 0323 15EE 15EF 0323 0323 0323 0323 0323 0323 
            0323 0323 15EE 15EF 0323 0323 1598 1599 1599 15B6 159E 159F 15BB 1599 5599 5598 
            15EB 15EC 15ED 0323 0323 0323 0323 0323 15EE 15EF 0323 0323 0323 0323 0323 0323 
            0323 0323 15EE 15EF 0323 0323 1598 1599 1599 15B7 15B8 15B9 15BA 1599 5599 5598 
            15FB 15FC 15FD 0323 0323 0323 0323 0323 15EE 15EF 0323 0323 0323 0323 0323 0323 
            15CD 0323 15EE 15EF 0323 0323 1598 1599 1599 1599 1599 1599 1599 1599 5599 5598 
            0323 0323 0323 0323 0323 0323 0323 0323 15EE 15EF 0323 0323 0323 15CA 15CB 15CC 
            15DD 0323 15EE 15EF 0323 0323 1598 1599 1599 1599 1599 1599 1599 1599 5599 5598 
            15C7 15C8 15C9 15C9 55C5 55C4 0323 0323 15EE 15EF 0323 0323 0323 15DA 15DB 15DC 
            15ED 0323 15EE 15EF 0323 0323 1598 1599 1599 1599 1599 1599 1599 1599 5599 5598 
            15D7 15D8 15D9 15D9 55D5 55D4 0323 0323 15EE 15EF 0323 0323 0323 15EA 15EB 15EC 
            15FD 0323 15EE 15EF 0323 0323 1598 1599 1599 1599 1599 1599 1599 1599 5599 5598 
            0323 0323 0323 0323 4323 55CE 15C4 15C5 15C6 15C6 55C5 55C5 15C9 15C9 55C5 55C4 
            0323 0323 15EE 15EF 0323 0323 1598 1599 1599 1599 1599 1599 1599 1599 5599 5598 
            0323 0323 0323 0323 4323 55CE 15D4 15D5 15D5 15D6 55D5 55D5 15D9 15D9 55D5 55D4 
            15C4 15C5 15C7 15C8 15C6 15C6 1598 1599 1599 1599 1599 1599 1599 1599 5599 5598 
            0323 0323 0323 0323 4323 55CE 15CE 0323 0323 0323 0323 0323 0323 0323 0323 55CE 
            15D4 15D5 15D7 15D8 15D5 15D6 1598 1599 1599 1599 1599 1599 1599 1599 5599 5598 
            0323 0323 0323 0323 4323 55CE 15CE 0323 0323 0323 0323 15CA 15CB 15CC 15CD 55CE 
            15CE 0323 0323 0323 0323 0323 1598 1599 1599 15AC 15AD 15AE 15AF 1599 5599 5598 
            160F 160F 160F 160F 4323 55CE 15CE 0323 0323 0323 0323 15DA 159C 159D 15DD 55CE 
            15CE 15CF 15CF 15CF 0323 0323 1598 1599 1599 15BC 15BD 15BE 15BF 1599 5599 5598 
            0323 0323 0323 0323 4323 55CE 15CE 0323 0323 0323 0323 15EA 159E 159F 15ED 55CE 
            15CE 0323 0323 0323 160F 160F 1598 1599 159A 159A 159A 159A 159A 159A 5599 5598 
            0323 0323 0323 0323 4323 55CE 15CE 0323 160F 160F 0323 15FA 15FB 15FC 15FD 55CE 
            15CE 0323 0323 0323 0323 0323 1598 1599 1599 1599 1599 1599 1599 1599 5599 5598 
            0323 0323 15CF 15CF 55CF 55CE 15CE 0323 0323 0323 0323 0323 0323 0323 0323 55CE 
            15CE 0323 0323 0323 0323 0323 1598 1599 1599 1599 1599 1599 1599 1599 5599 5598 
            0323 0323 0323 0323 4323 55CE 15CE 0323 0323 0323 0323 0323 0323 0323 4323 55CE 
            15CE 0323 0323 0323 0323 0323 1598 1599 1599 1599 1599 1599 1599 1599 5599 5598 
            0323 0323 0323 0323 4323 55CE 15CE 0323 0323 0323 0323 0323 0323 0323 4323 55CE 
            15CE 0323 0323 0323 0323 0323 1598 1599 1599 1599 1599 1599 1599 1599 5599 5598 
            0323 0323 0323 0323 4323 55CE 15CE 0323 0323 0323 0323 0323 0323 0323 4323 55CE 
            15CE 0323 0323 0323 0323 0323 1598 1599 1599 1599 1599 1599 1599 1599 5599 5598 
            0323 0323 0323 0323 4323 55CE 15CE 0323 0323 0323 0323 0323 0323 0323 4323 55CE 
          </SOURCE>
          <DEST>4000</DEST>
          <Section>Tiles2</Section>
        </Data>
      </BGData>
      <layer1_2>91D3</layer1_2>
    </State>
  </States>
</Room>